haikunator/__init__.py
haikunator/haikunator.py
haikunator/tests.py
haikunator-2.1.0.dist-info/DESCRIPTION.rst
haikunator-2.1.0.dist-info/METADATA
haikunator-2.1.0.dist-info/RECORD
haikunator-2.1.0.dist-info/WHEEL
haikunator-2.1.0.dist-info/metadata.json
haikunator-2.1.0.dist-info/top_level.txt
